skillman/__init__.py
skillman/claude_marketplace.py
skillman/cli.py
skillman/config.py
skillman/github.py
skillman/installer.py
skillman/models.py
skillman/utils.py
skillman-0.4.0.dist-info/METADATA
skillman-0.4.0.dist-info/WHEEL
skillman-0.4.0.dist-info/entry_points.txt
skillman-0.4.0.dist-info/top_level.txt
skillman-0.4.0.dist-info/RECORD
