Metadata-Version: 2.4
Name: skillman
Version: 0.4.0
Summary: CLI tool for managing Claude skills from GitHub repositories
Author-email: Chris von Csefalvay <chris@chrisvoncsefalvay.com>
License-Expression: MIT
Project-URL: Homepage, https://github.com/chrisvoncsefalvay/skillman
Project-URL: Documentation, https://github.com/chrisvoncsefalvay/skillman#readme
Project-URL: Repository, https://github.com/chrisvoncsefalvay/skillman.git
Project-URL: Issues, https://github.com/chrisvoncsefalvay/skillman/issues
Keywords: claude,skills,cli,tool,package-manager,github,ai
Classifier: Development Status :: 3 - Alpha
Classifier: Environment :: Console
Classifier: Intended Audience :: Developers
Classifier: Natural Language :: English
Classifier: Operating System :: OS Independent
Classifier: Programming Language :: Python :: 3
Classifier: Programming Language :: Python :: 3.9
Classifier: Programming Language :: Python :: 3.10
Classifier: Programming Language :: Python :: 3.11
Classifier: Programming Language :: Python :: 3.12
Classifier: Programming Language :: Python :: 3.13
Classifier: Topic :: Software Development :: Libraries
Classifier: Topic :: Utilities
Requires-Python: >=3.9
Requires-Dist: click>=8.0.0
Requires-Dist: rich>=13.0.0
Requires-Dist: GitPython>=3.1.0
Requires-Dist: tomli>=1.2.0; python_version < "3.11"
Requires-Dist: tomli_w>=1.0.0
Requires-Dist: requests>=2.25.0
Requires-Dist: PyYAML>=6.0
Provides-Extra: dev
Requires-Dist: pytest>=7.0.0; extra == "dev"
Requires-Dist: pytest-cov>=3.0.0; extra == "dev"
Requires-Dist: black>=22.0.0; extra == "dev"
Requires-Dist: flake8>=4.0.0; extra == "dev"
Requires-Dist: mypy>=0.950; extra == "dev"
